setup.py
tokyocabinet/__init__.py
tokyocabinet/btree.c
tokyocabinet/hash.c
tokyocabinet/table.c
tokyocabinet.egg-info/PKG-INFO
tokyocabinet.egg-info/SOURCES.txt
tokyocabinet.egg-info/dependency_links.txt
tokyocabinet.egg-info/top_level.txt