Metadata-Version: 1.0
Name: tokyocabinet
Version: 0.6
Summary: tokyocabinet aims to be a complete python wrapper for the 
Home-page: http://code.google.com/p/python-tokyocabinet/
Author: Elisha Cook
Author-email: ecook@justastudio.com
License: UNKNOWN
Platform: UNKNOWN
